{
  "id": "py-ley-3448",
  "type": "statute",
  "title": "Ley Nº 3394 / CONCEDE PENSION GRACIABLE AL SEÑOR CLEMENTE PIÑANEZ RUIZ DIAZ",
  "title_en": "Ley Nº 3394 / CONCEDE PENSION GRACIABLE AL SEÑOR CLEMENTE PIÑANEZ RUIZ DIAZ",
  "short_name": "Ley N° 3394",
  "status": "in_force",
  "issued_date": "2007-11-30",
  "in_force_date": "2007-12-07",
  "url": "https://www.bacn.gov.py/leyes-paraguayas/3448/ley-n-3394-concede-pension-graciable-al-senor-clemente-pinanez-ruiz-diaz",
  "provisions": [
    {
      "provision_ref": "art4",
      "section": "4",
      "title": "Artículo 4. Comuníquese al Poder Ejecutivo.",
      "content": "Aprobado el Proyecto de Ley por la Honorable Cámara de Senadores, a dos días del mes de agosto del año dos mil siete, quedando sancionado el mismo, por la Honorable Cámara de Diputados, a quince días del mes de noviembre del año dos mil siete, de conformidad a lo dispuesto en el Artículo 211 de la Constitución Nacional."
    }
  ],
  "definitions": []
}