{
  "id": "py-ley-4784",
  "type": "statute",
  "title": "Ley Nº 5576 / CREA LA COMISIÓN NACIONAL PARA EL ESTUDIO Y REFORMA DE LAS LEYES EN MATERIA DE NIÑEZ Y ADOLESCENCIA",
  "title_en": "Ley Nº 5576 / CREA LA COMISIÓN NACIONAL PARA EL ESTUDIO Y REFORMA DE LAS LEYES EN MATERIA DE NIÑEZ Y ADOLESCENCIA",
  "short_name": "Ley N° 5576",
  "status": "in_force",
  "issued_date": "2016-03-30",
  "in_force_date": "2016-03-31",
  "url": "https://www.bacn.gov.py/leyes-paraguayas/4784/ley-n-5576-crea-la-comision-nacional-para-el-estudio-y-reforma-de-las-leyes-en-materia-de-ninez-y-adolescencia",
  "provisions": [
    {
      "provision_ref": "art5",
      "section": "5",
      "title": "Artículo 5. Comuníquese al Poder Ejecutivo.",
      "content": "Aprobado el Proyecto de Ley por la Honorable Cámara de Senadores, a veinticuatro días del mes de setiembre del año dos mil quince, quedando sancionado el mismo, por la Honorable Cámara de Diputados, a diez días del mes de marzo del año dos mil dieciséis, de conformidad a lo dispuesto en el Artículo 204 de la Constitución Nacional."
    }
  ],
  "definitions": []
}