{
  "id": "py-ley-2177",
  "type": "statute",
  "title": "Ley Nº 3092 / CONCEDE PENSIÓN GRACIABLE AL SEÑOR ANTONIO GARCÍA VILLALBA.",
  "title_en": "Ley Nº 3092 / CONCEDE PENSIÓN GRACIABLE AL SEÑOR ANTONIO GARCÍA VILLALBA.",
  "short_name": "Ley N° 3092",
  "status": "in_force",
  "issued_date": "2006-11-14",
  "in_force_date": "2006-11-22",
  "url": "https://www.bacn.gov.py/leyes-paraguayas/2177/ley-n-3092-concede-pension-graciable-al-senor-antonio-garcia-villalba",
  "provisions": [
    {
      "provision_ref": "art4",
      "section": "4",
      "title": "Artículo 4. Comuníquese al Poder Ejecutivo.",
      "content": "Aprobado el Proyecto de Ley por la Honorable Cámara de Diputados, a los veinticinco días del mes de julio del año dos mil seis, y por la Honorable Cámara de Senadores, a los veintiséis días del mes de octubre del año dos mil seis, quedando sancionado el mismo, de conformidad con lo dispuesto en el Artículo 204 de la Constitución Nacional.\n \n \n \n \n Archivos adjuntos Antecedente \n Antecedente de la Ley Nº 00000003092 \n \n \n \n \n \n- Acápite: Que concede pensión graciable al Señor Antonio García Villalba\n \n \n \n \n \n \n- Fecha de sanción: 26/10/06\n \n \n \n \n \n \n- Camara: Senadores\n \n \n \n \n \n \n- Presentado por: Diputado Ignacio Mendoza\n \n \n \n \n \n \n- Codigo de Expediente: Pp221-06"
    }
  ],
  "definitions": []
}