{
  "id": "py-ley-2178",
  "type": "statute",
  "title": "Ley Nº 3093 / CREA LA UNIVERSIDAD DE SAN IGNACIO DE LOYOLA",
  "title_en": "Ley Nº 3093 / CREA LA UNIVERSIDAD DE SAN IGNACIO DE LOYOLA",
  "short_name": "Ley N° 3093",
  "status": "in_force",
  "issued_date": "2006-11-21",
  "in_force_date": "2006-11-24",
  "url": "https://www.bacn.gov.py/leyes-paraguayas/2178/ley-n-3093-crea-la-universidad-de-san-ignacio-de-loyola",
  "provisions": [
    {
      "provision_ref": "art2",
      "section": "2",
      "title": "Artículo 2. Comuníquese al Poder Ejecutivo.",
      "content": "Aprobado el Proyecto de Ley por la Honorable Cámara de Senadores, a veintiún días del mes de setiembre del año dos mil seis, quedando sancionado el mismo por la Honorable Cámara de Diputados, a dos días del mes de noviembre del año dos mil seis, de conformidad con lo dsipuesto en el Articulo de la Constitución Nacional. \n \n \n \n \n Archivos adjuntos Antecedente \n Antecedente de la Ley Nº 00000003093 \n \n \n \n \n \n- Acápite: Que crea la Universidad San Ignacio de Loyola\n \n \n \n \n \n \n- Fecha de sanción: 02/11/06\n \n \n \n \n \n \n- Camara: Diputados\n \n \n \n \n \n \n- Presentado por: Senador Alfredo Ratti\n \n \n \n \n \n \n- Codigo de Expediente: Pp222-06"
    }
  ],
  "definitions": []
}