{
  "id": "py-ley-2418",
  "type": "statute",
  "title": "Ley Nº 274 / APRUEBA EL DECRETO-LEY Nº 2340 DEL 30 DE DICIEMBRE DE 1950",
  "title_en": "Ley Nº 274 / APRUEBA EL DECRETO-LEY Nº 2340 DEL 30 DE DICIEMBRE DE 1950",
  "short_name": "Ley N° 274",
  "status": "in_force",
  "issued_date": "1955-08-04",
  "in_force_date": "1955-08-04",
  "url": "https://www.bacn.gov.py/leyes-paraguayas/2418/ley-n-274-aprueba-el-decreto-ley-n-2340-del-30-de-diciembre-de-1950",
  "provisions": [
    {
      "provision_ref": "art2",
      "section": "2",
      "title": "Artículo 2. Comuníquese al Poder Ejecutivo.",
      "content": "Dada en la Sala de Sesiones de la Honorable Cámara de Representantes a los veinte y nueve días del mes de julio del año un mil novecientos cincuenta y cinco."
    }
  ],
  "definitions": []
}