{
  "id": "py-ley-1538",
  "type": "statute",
  "title": "Ley Nº 3909 / CREA LA SECRETARÍA NACIONAL DE LA VIVIENDA Y EL HÁBITAT “SENAVITAT”.",
  "title_en": "Ley Nº 3909 / CREA LA SECRETARÍA NACIONAL DE LA VIVIENDA Y EL HÁBITAT “SENAVITAT”.",
  "short_name": "Ley N° 3909",
  "status": "in_force",
  "issued_date": "2010-06-07",
  "in_force_date": "2010-06-08",
  "url": "https://www.bacn.gov.py/leyes-paraguayas/1538/ley-n-3909-crea-la-secretaria-nacional-de-la-vivienda-y-el-habitat-senavitat",
  "provisions": [
    {
      "provision_ref": "art3",
      "section": "3",
      "title": "Artículo 3. Le compete a la SENAVITAT:",
      "content": "a) asumir la representación como máxima y exclusiva autoridad en cuestiones de políticas y acciones del sector habitacional;\n b) elevar al Poder Ejecutivo la propuesta de creación o modificación de leyes, decretos o normativas necesarias al ejercicio de su competencia; \n c) diseñar, coordinar, supervisar e implementar las políticas habitacionales y regular en materia de urbanismo para los programas y proyectos de la Secretaría, de acuerdo con las normativas vigentes y en coordinación con los municipios y gobernaciones afectados;\n d) diseñar las estrategias y acuerdos necesarios para el desarrollo de trabajos participativos con las organizaciones civiles;\n e) obtener y administrar recursos asignados para los fines específicos de la presente Ley y los fondos creados para el sector habitacional;\n f) suscribir convenios, acuerdos y otras formas de cooperación en materia de temas habitacionales y del hábitat que propicie la investigación e intercambio de conocimientos y experiencias, y movilice además los recursos nacionales y externos para la ejecución de planes y programas relacionados al sector habitacional y del hábitat;\n g) administrar los fondos destinados al sector habitacional, así como los previstos en la Ley N° 2.329/03 “QUE ESTABLECE EL MARCO DE ADMINISTRACIÓN DE LAS COOPERATIVAS DE VIVIENDA Y EL FONDO PARA VIVIENDAS COOPERATIVAS”;\n h) propiciar y realizar todo tipo de investigaciones y reglamentaciones referidas a la vivienda y el hábitat."
    },
    {
      "provision_ref": "art4",
      "section": "4",
      "title": "Artículo 4. Son funciones de la Secretaría:",
      "content": "a) diseñar, elaborar e implementar la política de Estado del sector habitacional a corto, mediano y largo plazo; y en función a ésta, diseñar e implementar los planes y programas de viviendas y hábitat urbanos, suburbanos, y rurales de diferentes tipologías con la inclusión de la infraestructura básica requerida para mejorar la calidad de vida de los beneficiarios, que favorezcan preferentemente a las familias de escasos recursos;\n b) coordinar y ejecutar las estrategias, priorizar los planes y velar por la gestión desarrollada por las áreas o unidades bajo su responsabilidad;\n c) diseñar y ejecutar programas específicos en base a características especiales, para sectores de la población en situación de pobreza y extrema pobreza;\n d) reglamentar, ejecutar, coordinar y evaluar la implementación de los sistemas de subsidios a ser otorgados, redescontar los créditos complementarios concedidos dentro del sistema, aplicar las multas y sanciones a los beneficiarios, instituciones de intermediación financieras (IFIs) y demás sujetos intervinientes dentro del sistema, conforme a los convenios, decretos y reglamentos que la institución dicte;\n e) reglamentar, ejecutar, coordinar y evaluar la implementación de los sistemas de ayuda mutua desarrollados por los beneficiarios con la colaboración y asesoramiento de las cooperativas, organizaciones sociales, gremios y otros;\n f) promover y coordinar la utilización de los fondos del FONAVIS previstos en los Artículos 4º y 5º de la Ley Nº 3.637/09 ;\n g) promover, coordinar, supervisar y evaluar la implementación de los proyectos encarados por cualquier entidad o institución pública que realice actividades relacionadas con los objetivos de la SENAVITAT, de tal forma que se adecuen a la política del sector;\n h) promover, coordinar, supervisar y evaluar las acciones realizadas por organizaciones civiles, en el marco de la política habitacional implementada por el gobierno nacional en función a la política del Estado paraguayo;\n i) ejecutar dentro de sus programas de construcción de viviendas, las obras de urbanización y saneamiento urbano, protegiendo el medio ambiente;\n j) implementar programas de Subsidios Habitacionales y de Redescuentos de Hipotecas dentro de los programas de la SENAVITAT;\n k) implementar programas de créditos hipotecarios a través de cooperativas, asociaciones, sindicatos y otros;\n l) propiciar programas que estimulen la participación de la sociedad civil;\n m) incentivar la participación de las comunidades sobre la base de programas de desarrollo social sostenibles;\n n) asesorar y prestar asistencia técnica a entidades estatales, privadas, organizaciones civiles, gobiernos departamentales y municipales, a solicitud de los mismos; así como también promover y coordinar con ellos las iniciativas que guarden relación con los fines de esta Ley;\n ñ) diseñar e implementar estrategias en los planes y programas, a fin de dar respuesta a las necesidades habitacionales de compatriotas con características especiales, como paraguayos residentes en el extranjero, repatriados, población indígena y otros, en coordinación con las instituciones u organizaciones correspondientes;\n o) diseñar e implementar un sistema para la adquisición de inmuebles urbanizados y de los asentamientos espontáneos existentes a la promulgación de la presente Ley, ubicados en áreas urbanas para beneficiarios de los estratos de bajos ingresos, utilizando los instrumentos jurídicos y urbanísticos adecuados;\n p) implementar un sistema de regularización de los inmuebles de los asentamientos espontáneos en áreas urbanas, que fueron adquiridos por el Estado dentro de los programas de regularización, impulsando y viabilizando su catastro, urbanización e integración a la ciudad, así como la actualización periódica de los registros de inmuebles de propiedad pública y privada."
    },
    {
      "provision_ref": "art6",
      "section": "6",
      "title": "Artículo 6. La Secretaría Nacional de la Vivienda y el Hábitat – SENAVITAT contará con las siguientes unidades orgánicas, conforme a la disponibilidad de este Título:",
      "content": "a. Secretaría Ejecutiva;\n b. Secretaría General;\n c. Direcciones;\n d Asesoría Jurídica;\n e. Auditoría Interna.\n Asimismo, se incluirá en la estructura, un área de coordinación con representantes de la sociedad civil organizada, del sector público y privado, cuya área de acción sea la problemática habitacional y el hábitat, a fin de coordinar e implementar los planes, programas y acciones de la Secretaría."
    },
    {
      "provision_ref": "art9",
      "section": "9",
      "title": "Artículo 9. El patrimonio y los recursos de la Secretaría Nacional de la Vivienda y el Hábitat - SENAVITAT se compondrán por:",
      "content": "a) los recursos provenientes de Fondos creados para el sector habitacional;\n b) los bienes que le trasfieran el Estado paraguayo o los que adquiera legalmente a cualquier título y los frutos de tales bienes;\n c) las asignaciones y subvenciones que se le destine en el Presupuesto General de la Nación; \n d) las rentas propias, las donaciones y los legados que reciba de fuentes nacionales o internacionales;\n e) los ingresos que se obtengan por los servicios que preste y por los permisos y concesiones de bienes y servicios que otorgue;\n f) los intereses, tasas o reajustes que se le acrediten en instituciones bancarias y financieras donde deposite haberes; \n g) las sumas y bienes que le transfieran los gobiernos departamentales y municipales para financiar los planes y programas de inversión acordados con los mismos;\n h) la totalidad del activo y pasivo del CONAVI constituido por muebles, inmuebles, derechos, acciones, garantías o privilegios, subrogándose de pleno derecho la Secretaría las acciones y derechos de esa Institución;\n i) los recursos provenientes de los fondos creados por la Ley N° 2.329/03 “QUE ESTABLECE EL MARCO DE ADMINISTRACIÓN DE LAS COOPERATIVAS DE VIVIENDA Y EL FONDO PARA VIVIENDAS COOPERATIVAS”;\n j) los ingresos por cobro de cuentas de viviendas construidas o financiadas por el CONAVI."
    },
    {
      "provision_ref": "art11",
      "section": "11",
      "title": "Artículo 11. Con la promulgación de la presente Ley, quedan derogadas las normas contenidas en la Ley Nº 118/90 del 9 de enero de 1991 “QUE CREA LA ENTIDAD AUTÁRQUICA ‘CONSEJO NACIONAL DE LA VIVIENDA’ (CONAVI) Y ESTABLECE SU CARTA ORGÁNICA”; y el Art. 4º, Inc. B) de la Ley Nº 3.637/09 QUE CREA EL FONDO NACIONAL DE LA VIVIENDA SOCIAL (FONAVIS), así como todas las disposiciones legales contrarias a la misma, transfiriéndose a la SENAVITAT los derechos, obligaciones, acciones, recursos presupuestarios que correspondían al CONAVI, entidad que queda extinguida, de conformidad a lo previsto en la presente Ley.",
      "content": "DISPOSICIONES TRANSITORIAS"
    },
    {
      "provision_ref": "art25",
      "section": "25",
      "title": "Artículo 25. Comuníquese al Poder Ejecutivo.",
      "content": "Aprobado el Proyecto de Ley por la Honorable Cámara de Diputados, a los catorce días del mes de julio del año dos mil nueve, y por la Honorable Cámara de Senadores, a los veintidós días del mes de octubre del año dos mil nueve, quedando sancionado el mismo, de conformidad con lo dispuesto en el Artículo 207, numeral 3 de la Constitución Nacional."
    }
  ],
  "definitions": []
}